{
  "version": 1,
  "exercises": [
    {
      "name": "Barbell Back Squat",
      "aliases": ["Back Squat", "Squat"],
      "primary_muscles": ["quads", "glutes"],
      "secondary_muscles": ["hamstrings", "adductors", "erectors"],
      "equipment": "barbell",
      "movement_pattern": "squat",
      "force_type": "push",
      "mechanics": "compound",
      "supports_bodyweight": false,
      "supports_incline": false,
      "supports_grip": false,
      "supports_stance": true,
      "default_rep_range": [5, 10],
      "default_sets": 3,
      "tags": ["powerlifting", "strength", "hypertrophy"]
    },
    {
      "name": "Barbell Front Squat",
      "aliases": ["Front Squat"],
      "primary_muscles": ["quads", "glutes"],
      "secondary_muscles": ["core", "erectors", "adductors"],
      "equipment": "barbell",
      "movement_pattern": "squat",
      "force_type": "push",
      "mechanics": "compound",
      "supports_bodyweight": false,
      "supports_incline": false,
      "supports_grip": false,
      "supports_stance": true,
      "default_rep_range": [5, 8],
      "default_sets": 3,
      "tags": ["strength", "hypertrophy", "olympic"]
    },
    {
      "name": "Hack Squat",
      "aliases": ["Machine Hack Squat"],
      "primary_muscles": ["quads"],
      "secondary_muscles": ["glutes", "hamstrings"],
      "equipment": "machine",
      "movement_pattern": "squat",
      "force_type": "push",
      "mechanics": "compound",
      "supports_bodyweight": false,
      "supports_incline": false,
      "supports_grip": false,
      "supports_stance": true,
      "default_rep_range": [8, 15],
      "default_sets": 3,
      "tags": ["hypertrophy"]
    },
    {
      "name": "Goblet Squat",
      "aliases": [],
      "primary_muscles": ["quads", "glutes"],
      "secondary_muscles": ["core", "adductors"],
      "equipment": "dumbbell",
      "movement_pattern": "squat",
      "force_type": "push",
      "mechanics": "compound",
      "supports_bodyweight": false,
      "supports_incline": false,
      "supports_grip": false,
      "supports_stance": true,
      "default_rep_range": [8, 15],
      "default_sets": 3,
      "tags": ["hypertrophy", "beginner"]
    },
    {
      "name": "Bulgarian Split Squat",
      "aliases": ["Rear Foot Elevated Split Squat", "RFESS"],
      "primary_muscles": ["quads", "glutes"],
      "secondary_muscles": ["hamstrings", "adductors"],
      "equipment": "dumbbell",
      "movement_pattern": "squat",
      "force_type": "push",
      "mechanics": "compound",
      "supports_bodyweight": true,
      "supports_incline": false,
      "supports_grip": false,
      "supports_stance": false,
      "default_rep_range": [8, 12],
      "default_sets": 3,
      "tags": ["hypertrophy", "unilateral"]
    },
    {
      "name": "Leg Press",
      "aliases": [],
      "primary_muscles": ["quads", "glutes"],
      "secondary_muscles": ["hamstrings", "adductors"],
      "equipment": "machine",
      "movement_pattern": "squat",
      "force_type": "push",
      "mechanics": "compound",
      "supports_bodyweight": false,
      "supports_incline": false,
      "supports_grip": false,
      "supports_stance": true,
      "default_rep_range": [8, 15],
      "default_sets": 3,
      "tags": ["hypertrophy"]
    },
    {
      "name": "Box Squat",
      "aliases": [],
      "primary_muscles": ["quads", "glutes", "hamstrings"],
      "secondary_muscles": ["erectors", "adductors"],
      "equipment": "barbell",
      "movement_pattern": "squat",
      "force_type": "push",
      "mechanics": "compound",
      "supports_bodyweight": false,
      "supports_incline": false,
      "supports_grip": false,
      "supports_stance": true,
      "default_rep_range": [3, 8],
      "default_sets": 3,
      "tags": ["powerlifting", "strength"]
    },
    {
      "name": "Dumbbell Squat",
      "aliases": [],
      "primary_muscles": ["quads", "glutes"],
      "secondary_muscles": ["hamstrings", "core"],
      "equipment": "dumbbell",
      "movement_pattern": "squat",
      "force_type": "push",
      "mechanics": "compound",
      "supports_bodyweight": false,
      "supports_incline": false,
      "supports_grip": false,
      "supports_stance": true,
      "default_rep_range": [10, 15],
      "default_sets": 3,
      "tags": ["hypertrophy", "beginner"]
    },
    {
      "name": "Zercher Squat",
      "aliases": [],
      "primary_muscles": ["quads", "glutes"],
      "secondary_muscles": ["core", "erectors", "biceps"],
      "equipment": "barbell",
      "movement_pattern": "squat",
      "force_type": "push",
      "mechanics": "compound",
      "supports_bodyweight": false,
      "supports_incline": false,
      "supports_grip": false,
      "supports_stance": true,
      "default_rep_range": [5, 10],
      "default_sets": 3,
      "tags": ["strength", "strongman"]
    },
    {
      "name": "Pause Squat",
      "aliases": [],
      "primary_muscles": ["quads", "glutes"],
      "secondary_muscles": ["hamstrings", "erectors"],
      "equipment": "barbell",
      "movement_pattern": "squat",
      "force_type": "push",
      "mechanics": "compound",
      "supports_bodyweight": false,
      "supports_incline": false,
      "supports_grip": false,
      "supports_stance": true,
      "default_rep_range": [3, 6],
      "default_sets": 3,
      "tags": ["powerlifting", "strength"]
    },
    {
      "name": "Belt Squat",
      "aliases": [],
      "primary_muscles": ["quads", "glutes"],
      "secondary_muscles": ["hamstrings", "adductors"],
      "equipment": "machine",
      "movement_pattern": "squat",
      "force_type": "push",
      "mechanics": "compound",
      "supports_bodyweight": false,
      "supports_incline": false,
      "supports_grip": false,
      "supports_stance": true,
      "default_rep_range": [8, 15],
      "default_sets": 3,
      "tags": ["hypertrophy", "spine-friendly"]
    },
    {
      "name": "Overhead Squat",
      "aliases": ["OHS"],
      "primary_muscles": ["quads", "glutes"],
      "secondary_muscles": ["core", "shoulders", "traps"],
      "equipment": "barbell",
      "movement_pattern": "squat",
      "force_type": "push",
      "mechanics": "compound",
      "supports_bodyweight": false,
      "supports_incline": false,
      "supports_grip": false,
      "supports_stance": true,
      "default_rep_range": [3, 6],
      "default_sets": 3,
      "tags": ["olympic", "strength"]
    },
    {
      "name": "Conventional Deadlift",
      "aliases": ["Deadlift"],
      "primary_muscles": ["hamstrings", "glutes", "erectors"],
      "secondary_muscles": ["quads", "traps", "lats", "forearms"],
      "equipment": "barbell",
      "movement_pattern": "hinge",
      "force_type": "pull",
      "mechanics": "compound",
      "supports_bodyweight": false,
      "supports_incline": false,
      "supports_grip": true,
      "supports_stance": false,
      "default_rep_range": [3, 6],
      "default_sets": 3,
      "tags": ["powerlifting", "strength"]
    },
    {
      "name": "Romanian Deadlift",
      "aliases": ["RDL"],
      "primary_muscles": ["hamstrings", "glutes"],
      "secondary_muscles": ["erectors", "adductors"],
      "equipment": "barbell",
      "movement_pattern": "hinge",
      "force_type": "pull",
      "mechanics": "compound",
      "supports_bodyweight": false,
      "supports_incline": false,
      "supports_grip": false,
      "supports_stance": false,
      "default_rep_range": [8, 12],
      "default_sets": 3,
      "tags": ["hypertrophy", "strength"]
    },
    {
      "name": "Sumo Deadlift",
      "aliases": [],
      "primary_muscles": ["glutes", "hamstrings", "adductors"],
      "secondary_muscles": ["quads", "erectors", "traps"],
      "equipment": "barbell",
      "movement_pattern": "hinge",
      "force_type": "pull",
      "mechanics": "compound",
      "supports_bodyweight": false,
      "supports_incline": false,
      "supports_grip": false,
      "supports_stance": false,
      "default_rep_range": [3, 6],
      "default_sets": 3,
      "tags": ["powerlifting", "strength"]
    },
    {
      "name": "Hip Thrust",
      "aliases": ["Barbell Hip Thrust"],
      "primary_muscles": ["glutes"],
      "secondary_muscles": ["hamstrings", "adductors", "core"],
      "equipment": "barbell",
      "movement_pattern": "hinge",
      "force_type": "push",
      "mechanics": "compound",
      "supports_bodyweight": true,
      "supports_incline": false,
      "supports_grip": false,
      "supports_stance": false,
      "default_rep_range": [8, 15],
      "default_sets": 3,
      "tags": ["hypertrophy", "glute"]
    },
    {
      "name": "Good Morning",
      "aliases": [],
      "primary_muscles": ["hamstrings", "glutes", "erectors"],
      "secondary_muscles": ["adductors"],
      "equipment": "barbell",
      "movement_pattern": "hinge",
      "force_type": "pull",
      "mechanics": "compound",
      "supports_bodyweight": false,
      "supports_incline": false,
      "supports_grip": false,
      "supports_stance": false,
      "default_rep_range": [8, 12],
      "default_sets": 3,
      "tags": ["strength", "hypertrophy"]
    },
    {
      "name": "Trap Bar Deadlift",
      "aliases": ["Hex Bar Deadlift"],
      "primary_muscles": ["quads", "glutes", "hamstrings"],
      "secondary_muscles": ["erectors", "traps", "forearms"],
      "equipment": "barbell",
      "movement_pattern": "hinge",
      "force_type": "pull",
      "mechanics": "compound",
      "supports_bodyweight": false,
      "supports_incline": false,
      "supports_grip": false,
      "supports_stance": false,
      "default_rep_range": [4, 8],
      "default_sets": 3,
      "tags": ["strength", "beginner-friendly"]
    },
    {
      "name": "Stiff-Leg Deadlift",
      "aliases": ["SLDL", "Straight-Leg Deadlift"],
      "primary_muscles": ["hamstrings", "glutes"],
      "secondary_muscles": ["erectors"],
      "equipment": "barbell",
      "movement_pattern": "hinge",
      "force_type": "pull",
      "mechanics": "compound",
      "supports_bodyweight": false,
      "supports_incline": false,
      "supports_grip": false,
      "supports_stance": false,
      "default_rep_range": [8, 12],
      "default_sets": 3,
      "tags": ["hypertrophy"]
    },
    {
      "name": "Single-Leg Romanian Deadlift",
      "aliases": ["Single-Leg RDL", "SL-RDL"],
      "primary_muscles": ["hamstrings", "glutes"],
      "secondary_muscles": ["core", "adductors"],
      "equipment": "dumbbell",
      "movement_pattern": "hinge",
      "force_type": "pull",
      "mechanics": "compound",
      "supports_bodyweight": false,
      "supports_incline": false,
      "supports_grip": false,
      "supports_stance": false,
      "default_rep_range": [8, 12],
      "default_sets": 3,
      "tags": ["hypertrophy", "unilateral"]
    },
    {
      "name": "Kettlebell Swing",
      "aliases": ["KB Swing"],
      "primary_muscles": ["glutes", "hamstrings"],
      "secondary_muscles": ["core", "erectors", "shoulders"],
      "equipment": "kettlebell",
      "movement_pattern": "hinge",
      "force_type": "pull",
      "mechanics": "compound",
      "supports_bodyweight": false,
      "supports_incline": false,
      "supports_grip": false,
      "supports_stance": false,
      "default_rep_range": [10, 20],
      "default_sets": 3,
      "tags": ["conditioning", "power"]
    },
    {
      "name": "Nordic Curl",
      "aliases": ["Nordic Hamstring Curl"],
      "primary_muscles": ["hamstrings"],
      "secondary_muscles": ["glutes"],
      "equipment": "bodyweight",
      "movement_pattern": "hinge",
      "force_type": "pull",
      "mechanics": "isolation",
      "supports_bodyweight": true,
      "supports_incline": false,
      "supports_grip": false,
      "supports_stance": false,
      "default_rep_range": [3, 8],
      "default_sets": 3,
      "tags": ["hypertrophy", "injury-prevention"]
    },
    {
      "name": "Barbell Bench Press",
      "aliases": ["Bench Press", "Flat Bench"],
      "primary_muscles": ["chest"],
      "secondary_muscles": ["triceps", "anterior_deltoid"],
      "equipment": "barbell",
      "movement_pattern": "push_horizontal",
      "force_type": "push",
      "mechanics": "compound",
      "supports_bodyweight": false,
      "supports_incline": false,
      "supports_grip": true,
      "supports_stance": false,
      "default_rep_range": [5, 10],
      "default_sets": 3,
      "tags": ["powerlifting", "strength", "hypertrophy"]
    },
    {
      "name": "Incline Barbell Bench Press",
      "aliases": ["Incline Bench"],
      "primary_muscles": ["chest", "anterior_deltoid"],
      "secondary_muscles": ["triceps"],
      "equipment": "barbell",
      "movement_pattern": "push_horizontal",
      "force_type": "push",
      "mechanics": "compound",
      "supports_bodyweight": false,
      "supports_incline": true,
      "supports_grip": false,
      "supports_stance": false,
      "default_rep_range": [6, 10],
      "default_sets": 3,
      "tags": ["hypertrophy", "strength"]
    },
    {
      "name": "Decline Barbell Bench Press",
      "aliases": ["Decline Bench"],
      "primary_muscles": ["chest"],
      "secondary_muscles": ["triceps", "anterior_deltoid"],
      "equipment": "barbell",
      "movement_pattern": "push_horizontal",
      "force_type": "push",
      "mechanics": "compound",
      "supports_bodyweight": false,
      "supports_incline": true,
      "supports_grip": false,
      "supports_stance": false,
      "default_rep_range": [8, 12],
      "default_sets": 3,
      "tags": ["hypertrophy"]
    },
    {
      "name": "Dumbbell Bench Press",
      "aliases": ["DB Bench"],
      "primary_muscles": ["chest"],
      "secondary_muscles": ["triceps", "anterior_deltoid"],
      "equipment": "dumbbell",
      "movement_pattern": "push_horizontal",
      "force_type": "push",
      "mechanics": "compound",
      "supports_bodyweight": false,
      "supports_incline": false,
      "supports_grip": false,
      "supports_stance": false,
      "default_rep_range": [8, 12],
      "default_sets": 3,
      "tags": ["hypertrophy"]
    },
    {
      "name": "Incline Dumbbell Press",
      "aliases": ["Incline DB Press"],
      "primary_muscles": ["chest", "anterior_deltoid"],
      "secondary_muscles": ["triceps"],
      "equipment": "dumbbell",
      "movement_pattern": "push_horizontal",
      "force_type": "push",
      "mechanics": "compound",
      "supports_bodyweight": false,
      "supports_incline": true,
      "supports_grip": false,
      "supports_stance": false,
      "default_rep_range": [8, 12],
      "default_sets": 3,
      "tags": ["hypertrophy"]
    },
    {
      "name": "Cable Chest Flye",
      "aliases": ["Cable Flye", "Cable Crossover"],
      "primary_muscles": ["chest"],
      "secondary_muscles": ["anterior_deltoid"],
      "equipment": "cable",
      "movement_pattern": "push_horizontal",
      "force_type": "push",
      "mechanics": "isolation",
      "supports_bodyweight": false,
      "supports_incline": true,
      "supports_grip": false,
      "supports_stance": false,
      "default_rep_range": [10, 15],
      "default_sets": 3,
      "tags": ["hypertrophy", "isolation"]
    },
    {
      "name": "Push-Up",
      "aliases": ["Press-Up"],
      "primary_muscles": ["chest", "triceps"],
      "secondary_muscles": ["anterior_deltoid", "serratus"],
      "equipment": "bodyweight",
      "movement_pattern": "push_horizontal",
      "force_type": "push",
      "mechanics": "compound",
      "supports_bodyweight": true,
      "supports_incline": true,
      "supports_grip": true,
      "supports_stance": false,
      "default_rep_range": [8, 20],
      "default_sets": 3,
      "tags": ["calisthenics", "hypertrophy", "beginner"]
    },
    {
      "name": "Chest Dips",
      "aliases": ["Dips (Chest)", "Weighted Dips"],
      "primary_muscles": ["chest", "triceps"],
      "secondary_muscles": ["anterior_deltoid"],
      "equipment": "bodyweight",
      "movement_pattern": "push_horizontal",
      "force_type": "push",
      "mechanics": "compound",
      "supports_bodyweight": true,
      "supports_incline": false,
      "supports_grip": false,
      "supports_stance": false,
      "default_rep_range": [6, 12],
      "default_sets": 3,
      "tags": ["calisthenics", "hypertrophy", "strength"]
    },
    {
      "name": "Machine Chest Press",
      "aliases": ["Chest Press Machine"],
      "primary_muscles": ["chest"],
      "secondary_muscles": ["triceps", "anterior_deltoid"],
      "equipment": "machine",
      "movement_pattern": "push_horizontal",
      "force_type": "push",
      "mechanics": "compound",
      "supports_bodyweight": false,
      "supports_incline": false,
      "supports_grip": false,
      "supports_stance": false,
      "default_rep_range": [10, 15],
      "default_sets": 3,
      "tags": ["hypertrophy", "beginner"]
    },
    {
      "name": "Pec Deck",
      "aliases": ["Machine Flye"],
      "primary_muscles": ["chest"],
      "secondary_muscles": ["anterior_deltoid"],
      "equipment": "machine",
      "movement_pattern": "push_horizontal",
      "force_type": "push",
      "mechanics": "isolation",
      "supports_bodyweight": false,
      "supports_incline": false,
      "supports_grip": false,
      "supports_stance": false,
      "default_rep_range": [10, 15],
      "default_sets": 3,
      "tags": ["hypertrophy", "isolation"]
    },
    {
      "name": "Landmine Press",
      "aliases": [],
      "primary_muscles": ["chest", "anterior_deltoid"],
      "secondary_muscles": ["triceps", "serratus"],
      "equipment": "barbell",
      "movement_pattern": "push_horizontal",
      "force_type": "push",
      "mechanics": "compound",
      "supports_bodyweight": false,
      "supports_incline": false,
      "supports_grip": false,
      "supports_stance": false,
      "default_rep_range": [8, 12],
      "default_sets": 3,
      "tags": ["hypertrophy", "shoulder-friendly"]
    },
    {
      "name": "Overhead Press",
      "aliases": ["Military Press", "OHP", "Barbell Overhead Press"],
      "primary_muscles": ["anterior_deltoid", "lateral_deltoid"],
      "secondary_muscles": ["triceps", "traps", "serratus"],
      "equipment": "barbell",
      "movement_pattern": "push_vertical",
      "force_type": "push",
      "mechanics": "compound",
      "supports_bodyweight": false,
      "supports_incline": false,
      "supports_grip": true,
      "supports_stance": false,
      "default_rep_range": [5, 8],
      "default_sets": 3,
      "tags": ["strength", "hypertrophy"]
    },
    {
      "name": "Dumbbell Shoulder Press",
      "aliases": ["DB Shoulder Press", "DB OHP"],
      "primary_muscles": ["anterior_deltoid", "lateral_deltoid"],
      "secondary_muscles": ["triceps", "traps"],
      "equipment": "dumbbell",
      "movement_pattern": "push_vertical",
      "force_type": "push",
      "mechanics": "compound",
      "supports_bodyweight": false,
      "supports_incline": false,
      "supports_grip": false,
      "supports_stance": false,
      "default_rep_range": [8, 12],
      "default_sets": 3,
      "tags": ["hypertrophy"]
    },
    {
      "name": "Arnold Press",
      "aliases": [],
      "primary_muscles": ["anterior_deltoid", "lateral_deltoid"],
      "secondary_muscles": ["triceps"],
      "equipment": "dumbbell",
      "movement_pattern": "push_vertical",
      "force_type": "push",
      "mechanics": "compound",
      "supports_bodyweight": false,
      "supports_incline": false,
      "supports_grip": false,
      "supports_stance": false,
      "default_rep_range": [8, 12],
      "default_sets": 3,
      "tags": ["hypertrophy"]
    },
    {
      "name": "Machine Shoulder Press",
      "aliases": ["Plate-Loaded Shoulder Press"],
      "primary_muscles": ["anterior_deltoid", "lateral_deltoid"],
      "secondary_muscles": ["triceps"],
      "equipment": "machine",
      "movement_pattern": "push_vertical",
      "force_type": "push",
      "mechanics": "compound",
      "supports_bodyweight": false,
      "supports_incline": false,
      "supports_grip": false,
      "supports_stance": false,
      "default_rep_range": [10, 15],
      "default_sets": 3,
      "tags": ["hypertrophy", "beginner"]
    },
    {
      "name": "Lateral Raise",
      "aliases": ["DB Lateral Raise", "Side Raise"],
      "primary_muscles": ["lateral_deltoid"],
      "secondary_muscles": ["traps"],
      "equipment": "dumbbell",
      "movement_pattern": "push_vertical",
      "force_type": "push",
      "mechanics": "isolation",
      "supports_bodyweight": false,
      "supports_incline": false,
      "supports_grip": false,
      "supports_stance": false,
      "default_rep_range": [12, 20],
      "default_sets": 3,
      "tags": ["hypertrophy", "isolation"]
    },
    {
      "name": "Cable Lateral Raise",
      "aliases": [],
      "primary_muscles": ["lateral_deltoid"],
      "secondary_muscles": [],
      "equipment": "cable",
      "movement_pattern": "push_vertical",
      "force_type": "push",
      "mechanics": "isolation",
      "supports_bodyweight": false,
      "supports_incline": false,
      "supports_grip": false,
      "supports_stance": false,
      "default_rep_range": [12, 20],
      "default_sets": 3,
      "tags": ["hypertrophy", "isolation"]
    },
    {
      "name": "Push Press",
      "aliases": [],
      "primary_muscles": ["anterior_deltoid", "triceps"],
      "secondary_muscles": ["quads", "glutes", "traps"],
      "equipment": "barbell",
      "movement_pattern": "push_vertical",
      "force_type": "push",
      "mechanics": "compound",
      "supports_bodyweight": false,
      "supports_incline": false,
      "supports_grip": false,
      "supports_stance": false,
      "default_rep_range": [3, 6],
      "default_sets": 3,
      "tags": ["power", "strength", "olympic"]
    },
    {
      "name": "Z-Press",
      "aliases": ["Seated Floor Press"],
      "primary_muscles": ["anterior_deltoid", "lateral_deltoid"],
      "secondary_muscles": ["triceps", "core"],
      "equipment": "barbell",
      "movement_pattern": "push_vertical",
      "force_type": "push",
      "mechanics": "compound",
      "supports_bodyweight": false,
      "supports_incline": false,
      "supports_grip": false,
      "supports_stance": false,
      "default_rep_range": [5, 8],
      "default_sets": 3,
      "tags": ["strength", "core"]
    },
    {
      "name": "Barbell Row",
      "aliases": ["Bent-Over Row", "Bent-Over Barbell Row"],
      "primary_muscles": ["lats", "traps"],
      "secondary_muscles": ["biceps", "rear_deltoid", "erectors"],
      "equipment": "barbell",
      "movement_pattern": "pull_horizontal",
      "force_type": "pull",
      "mechanics": "compound",
      "supports_bodyweight": false,
      "supports_incline": false,
      "supports_grip": true,
      "supports_stance": false,
      "default_rep_range": [5, 10],
      "default_sets": 3,
      "tags": ["strength", "hypertrophy"]
    },
    {
      "name": "Dumbbell Row",
      "aliases": ["DB Row", "One-Arm Dumbbell Row"],
      "primary_muscles": ["lats", "traps"],
      "secondary_muscles": ["biceps", "rear_deltoid"],
      "equipment": "dumbbell",
      "movement_pattern": "pull_horizontal",
      "force_type": "pull",
      "mechanics": "compound",
      "supports_bodyweight": false,
      "supports_incline": false,
      "supports_grip": false,
      "supports_stance": false,
      "default_rep_range": [8, 12],
      "default_sets": 3,
      "tags": ["hypertrophy"]
    },
    {
      "name": "Cable Row",
      "aliases": ["Seated Cable Row"],
      "primary_muscles": ["lats", "traps"],
      "secondary_muscles": ["biceps", "rear_deltoid"],
      "equipment": "cable",
      "movement_pattern": "pull_horizontal",
      "force_type": "pull",
      "mechanics": "compound",
      "supports_bodyweight": false,
      "supports_incline": false,
      "supports_grip": true,
      "supports_stance": false,
      "default_rep_range": [8, 12],
      "default_sets": 3,
      "tags": ["hypertrophy"]
    },
    {
      "name": "Machine Row",
      "aliases": ["Chest-Supported Machine Row"],
      "primary_muscles": ["lats", "traps"],
      "secondary_muscles": ["biceps", "rear_deltoid"],
      "equipment": "machine",
      "movement_pattern": "pull_horizontal",
      "force_type": "pull",
      "mechanics": "compound",
      "supports_bodyweight": false,
      "supports_incline": false,
      "supports_grip": false,
      "supports_stance": false,
      "default_rep_range": [8, 15],
      "default_sets": 3,
      "tags": ["hypertrophy", "beginner"]
    },
    {
      "name": "Chest-Supported Row",
      "aliases": ["Incline DB Row"],
      "primary_muscles": ["lats", "traps"],
      "secondary_muscles": ["biceps", "rear_deltoid"],
      "equipment": "dumbbell",
      "movement_pattern": "pull_horizontal",
      "force_type": "pull",
      "mechanics": "compound",
      "supports_bodyweight": false,
      "supports_incline": false,
      "supports_grip": false,
      "supports_stance": false,
      "default_rep_range": [10, 15],
      "default_sets": 3,
      "tags": ["hypertrophy"]
    },
    {
      "name": "T-Bar Row",
      "aliases": [],
      "primary_muscles": ["lats", "traps"],
      "secondary_muscles": ["biceps", "rear_deltoid", "erectors"],
      "equipment": "barbell",
      "movement_pattern": "pull_horizontal",
      "force_type": "pull",
      "mechanics": "compound",
      "supports_bodyweight": false,
      "supports_incline": false,
      "supports_grip": true,
      "supports_stance": false,
      "default_rep_range": [6, 10],
      "default_sets": 3,
      "tags": ["hypertrophy", "strength"]
    },
    {
      "name": "Pendlay Row",
      "aliases": [],
      "primary_muscles": ["lats", "traps", "erectors"],
      "secondary_muscles": ["biceps", "rear_deltoid"],
      "equipment": "barbell",
      "movement_pattern": "pull_horizontal",
      "force_type": "pull",
      "mechanics": "compound",
      "supports_bodyweight": false,
      "supports_incline": false,
      "supports_grip": false,
      "supports_stance": false,
      "default_rep_range": [4, 8],
      "default_sets": 3,
      "tags": ["strength", "power"]
    },
    {
      "name": "Meadows Row",
      "aliases": [],
      "primary_muscles": ["lats"],
      "secondary_muscles": ["biceps", "rear_deltoid"],
      "equipment": "barbell",
      "movement_pattern": "pull_horizontal",
      "force_type": "pull",
      "mechanics": "compound",
      "supports_bodyweight": false,
      "supports_incline": false,
      "supports_grip": false,
      "supports_stance": false,
      "default_rep_range": [8, 12],
      "default_sets": 3,
      "tags": ["hypertrophy"]
    },
    {
      "name": "Pull-Up",
      "aliases": ["Pullup"],
      "primary_muscles": ["lats"],
      "secondary_muscles": ["biceps", "rear_deltoid", "traps"],
      "equipment": "bodyweight",
      "movement_pattern": "pull_vertical",
      "force_type": "pull",
      "mechanics": "compound",
      "supports_bodyweight": true,
      "supports_incline": false,
      "supports_grip": true,
      "supports_stance": false,
      "default_rep_range": [5, 12],
      "default_sets": 3,
      "tags": ["calisthenics", "strength", "hypertrophy"]
    },
    {
      "name": "Chin-Up",
      "aliases": ["Chinup"],
      "primary_muscles": ["lats", "biceps"],
      "secondary_muscles": ["rear_deltoid", "traps"],
      "equipment": "bodyweight",
      "movement_pattern": "pull_vertical",
      "force_type": "pull",
      "mechanics": "compound",
      "supports_bodyweight": true,
      "supports_incline": false,
      "supports_grip": false,
      "supports_stance": false,
      "default_rep_range": [5, 12],
      "default_sets": 3,
      "tags": ["calisthenics", "strength", "hypertrophy"]
    },
    {
      "name": "Lat Pulldown",
      "aliases": ["Lat Pull-Down"],
      "primary_muscles": ["lats"],
      "secondary_muscles": ["biceps", "rear_deltoid"],
      "equipment": "cable",
      "movement_pattern": "pull_vertical",
      "force_type": "pull",
      "mechanics": "compound",
      "supports_bodyweight": false,
      "supports_incline": false,
      "supports_grip": true,
      "supports_stance": false,
      "default_rep_range": [8, 12],
      "default_sets": 3,
      "tags": ["hypertrophy", "beginner"]
    },
    {
      "name": "Cable Pullover",
      "aliases": ["Cable Lat Pullover"],
      "primary_muscles": ["lats"],
      "secondary_muscles": ["serratus", "triceps"],
      "equipment": "cable",
      "movement_pattern": "pull_vertical",
      "force_type": "pull",
      "mechanics": "isolation",
      "supports_bodyweight": false,
      "supports_incline": false,
      "supports_grip": false,
      "supports_stance": false,
      "default_rep_range": [10, 15],
      "default_sets": 3,
      "tags": ["hypertrophy", "isolation"]
    },
    {
      "name": "Straight-Arm Pulldown",
      "aliases": [],
      "primary_muscles": ["lats"],
      "secondary_muscles": ["serratus"],
      "equipment": "cable",
      "movement_pattern": "pull_vertical",
      "force_type": "pull",
      "mechanics": "isolation",
      "supports_bodyweight": false,
      "supports_incline": false,
      "supports_grip": false,
      "supports_stance": false,
      "default_rep_range": [10, 15],
      "default_sets": 3,
      "tags": ["hypertrophy", "isolation"]
    },
    {
      "name": "Neutral-Grip Pull-Up",
      "aliases": ["Hammer Grip Pull-Up"],
      "primary_muscles": ["lats", "biceps"],
      "secondary_muscles": ["rear_deltoid", "traps"],
      "equipment": "bodyweight",
      "movement_pattern": "pull_vertical",
      "force_type": "pull",
      "mechanics": "compound",
      "supports_bodyweight": true,
      "supports_incline": false,
      "supports_grip": false,
      "supports_stance": false,
      "default_rep_range": [5, 12],
      "default_sets": 3,
      "tags": ["calisthenics", "hypertrophy"]
    },
    {
      "name": "Single-Arm Lat Pulldown",
      "aliases": ["Single-Arm Cable Pulldown"],
      "primary_muscles": ["lats"],
      "secondary_muscles": ["biceps"],
      "equipment": "cable",
      "movement_pattern": "pull_vertical",
      "force_type": "pull",
      "mechanics": "compound",
      "supports_bodyweight": false,
      "supports_incline": false,
      "supports_grip": false,
      "supports_stance": false,
      "default_rep_range": [10, 15],
      "default_sets": 3,
      "tags": ["hypertrophy", "unilateral"]
    },
    {
      "name": "MTS Row",
      "aliases": ["Machine Single-Arm Row"],
      "primary_muscles": ["lats"],
      "secondary_muscles": ["biceps", "rear_deltoid"],
      "equipment": "machine",
      "movement_pattern": "pull_vertical",
      "force_type": "pull",
      "mechanics": "compound",
      "supports_bodyweight": false,
      "supports_incline": false,
      "supports_grip": false,
      "supports_stance": false,
      "default_rep_range": [8, 15],
      "default_sets": 3,
      "tags": ["hypertrophy"]
    },
    {
      "name": "Farmer Carry",
      "aliases": ["Farmer's Walk"],
      "primary_muscles": ["traps", "forearms", "core"],
      "secondary_muscles": ["quads", "glutes"],
      "equipment": "dumbbell",
      "movement_pattern": "carry",
      "force_type": "static",
      "mechanics": "compound",
      "supports_bodyweight": false,
      "supports_incline": false,
      "supports_grip": false,
      "supports_stance": false,
      "default_rep_range": [1, 1],
      "default_sets": 3,
      "tags": ["strongman", "conditioning", "grip"]
    },
    {
      "name": "Suitcase Carry",
      "aliases": ["Single-Arm Farmer Carry"],
      "primary_muscles": ["core", "traps", "forearms"],
      "secondary_muscles": ["glutes", "quads"],
      "equipment": "dumbbell",
      "movement_pattern": "carry",
      "force_type": "static",
      "mechanics": "compound",
      "supports_bodyweight": false,
      "supports_incline": false,
      "supports_grip": false,
      "supports_stance": false,
      "default_rep_range": [1, 1],
      "default_sets": 3,
      "tags": ["core", "unilateral", "conditioning"]
    },
    {
      "name": "Yoke Carry",
      "aliases": [],
      "primary_muscles": ["traps", "core", "glutes"],
      "secondary_muscles": ["quads", "erectors"],
      "equipment": "other",
      "movement_pattern": "carry",
      "force_type": "static",
      "mechanics": "compound",
      "supports_bodyweight": false,
      "supports_incline": false,
      "supports_grip": false,
      "supports_stance": false,
      "default_rep_range": [1, 1],
      "default_sets": 3,
      "tags": ["strongman", "conditioning"]
    },
    {
      "name": "Overhead Carry",
      "aliases": ["Waiter Walk"],
      "primary_muscles": ["shoulders", "core"],
      "secondary_muscles": ["traps", "triceps"],
      "equipment": "dumbbell",
      "movement_pattern": "carry",
      "force_type": "static",
      "mechanics": "compound",
      "supports_bodyweight": false,
      "supports_incline": false,
      "supports_grip": false,
      "supports_stance": false,
      "default_rep_range": [1, 1],
      "default_sets": 3,
      "tags": ["core", "conditioning"]
    },
    {
      "name": "Plank",
      "aliases": ["Front Plank"],
      "primary_muscles": ["core", "abs"],
      "secondary_muscles": ["shoulders", "glutes"],
      "equipment": "bodyweight",
      "movement_pattern": "core",
      "force_type": "static",
      "mechanics": "isolation",
      "supports_bodyweight": true,
      "supports_incline": false,
      "supports_grip": false,
      "supports_stance": false,
      "default_rep_range": [1, 1],
      "default_sets": 3,
      "tags": ["core", "beginner"]
    },
    {
      "name": "Side Plank",
      "aliases": [],
      "primary_muscles": ["core", "abs"],
      "secondary_muscles": ["glutes", "lateral_deltoid"],
      "equipment": "bodyweight",
      "movement_pattern": "core",
      "force_type": "static",
      "mechanics": "isolation",
      "supports_bodyweight": true,
      "supports_incline": false,
      "supports_grip": false,
      "supports_stance": false,
      "default_rep_range": [1, 1],
      "default_sets": 3,
      "tags": ["core"]
    },
    {
      "name": "Ab Wheel Rollout",
      "aliases": ["Ab Wheel"],
      "primary_muscles": ["abs", "core"],
      "secondary_muscles": ["lats", "shoulders"],
      "equipment": "other",
      "movement_pattern": "core",
      "force_type": "push",
      "mechanics": "compound",
      "supports_bodyweight": true,
      "supports_incline": false,
      "supports_grip": false,
      "supports_stance": false,
      "default_rep_range": [5, 10],
      "default_sets": 3,
      "tags": ["core", "hypertrophy"]
    },
    {
      "name": "Hanging Leg Raise",
      "aliases": ["HLR"],
      "primary_muscles": ["abs", "hip_flexors"],
      "secondary_muscles": ["core"],
      "equipment": "bodyweight",
      "movement_pattern": "core",
      "force_type": "pull",
      "mechanics": "isolation",
      "supports_bodyweight": true,
      "supports_incline": false,
      "supports_grip": false,
      "supports_stance": false,
      "default_rep_range": [8, 15],
      "default_sets": 3,
      "tags": ["core", "calisthenics"]
    },
    {
      "name": "Hanging Knee Raise",
      "aliases": [],
      "primary_muscles": ["abs", "hip_flexors"],
      "secondary_muscles": ["core"],
      "equipment": "bodyweight",
      "movement_pattern": "core",
      "force_type": "pull",
      "mechanics": "isolation",
      "supports_bodyweight": true,
      "supports_incline": false,
      "supports_grip": false,
      "supports_stance": false,
      "default_rep_range": [10, 20],
      "default_sets": 3,
      "tags": ["core", "beginner"]
    },
    {
      "name": "Cable Crunch",
      "aliases": ["Kneeling Cable Crunch"],
      "primary_muscles": ["abs"],
      "secondary_muscles": ["core"],
      "equipment": "cable",
      "movement_pattern": "core",
      "force_type": "pull",
      "mechanics": "isolation",
      "supports_bodyweight": false,
      "supports_incline": false,
      "supports_grip": false,
      "supports_stance": false,
      "default_rep_range": [10, 15],
      "default_sets": 3,
      "tags": ["hypertrophy", "isolation"]
    },
    {
      "name": "Dead Bug",
      "aliases": [],
      "primary_muscles": ["abs", "core"],
      "secondary_muscles": ["hip_flexors"],
      "equipment": "bodyweight",
      "movement_pattern": "core",
      "force_type": "static",
      "mechanics": "isolation",
      "supports_bodyweight": true,
      "supports_incline": false,
      "supports_grip": false,
      "supports_stance": false,
      "default_rep_range": [8, 12],
      "default_sets": 3,
      "tags": ["core", "beginner", "rehab"]
    },
    {
      "name": "Bird Dog",
      "aliases": [],
      "primary_muscles": ["core", "glutes"],
      "secondary_muscles": ["erectors"],
      "equipment": "bodyweight",
      "movement_pattern": "core",
      "force_type": "static",
      "mechanics": "isolation",
      "supports_bodyweight": true,
      "supports_incline": false,
      "supports_grip": false,
      "supports_stance": false,
      "default_rep_range": [8, 12],
      "default_sets": 3,
      "tags": ["core", "beginner", "rehab"]
    },
    {
      "name": "Pallof Press",
      "aliases": [],
      "primary_muscles": ["core", "abs"],
      "secondary_muscles": ["shoulders"],
      "equipment": "cable",
      "movement_pattern": "core",
      "force_type": "push",
      "mechanics": "isolation",
      "supports_bodyweight": false,
      "supports_incline": false,
      "supports_grip": false,
      "supports_stance": false,
      "default_rep_range": [10, 15],
      "default_sets": 3,
      "tags": ["core", "anti-rotation"]
    },
    {
      "name": "L-Sit",
      "aliases": [],
      "primary_muscles": ["abs", "hip_flexors", "core"],
      "secondary_muscles": ["triceps", "shoulders"],
      "equipment": "bodyweight",
      "movement_pattern": "core",
      "force_type": "static",
      "mechanics": "isolation",
      "supports_bodyweight": true,
      "supports_incline": false,
      "supports_grip": false,
      "supports_stance": false,
      "default_rep_range": [1, 1],
      "default_sets": 3,
      "tags": ["calisthenics", "core"]
    },
    {
      "name": "Dragon Flag",
      "aliases": [],
      "primary_muscles": ["abs", "core"],
      "secondary_muscles": ["lats", "hip_flexors"],
      "equipment": "bodyweight",
      "movement_pattern": "core",
      "force_type": "pull",
      "mechanics": "compound",
      "supports_bodyweight": true,
      "supports_incline": false,
      "supports_grip": false,
      "supports_stance": false,
      "default_rep_range": [3, 8],
      "default_sets": 3,
      "tags": ["calisthenics", "core", "advanced"]
    },
    {
      "name": "Barbell Curl",
      "aliases": ["Bicep Curl", "Straight Bar Curl"],
      "primary_muscles": ["biceps"],
      "secondary_muscles": ["forearms"],
      "equipment": "barbell",
      "movement_pattern": "isolation",
      "force_type": "pull",
      "mechanics": "isolation",
      "supports_bodyweight": false,
      "supports_incline": false,
      "supports_grip": true,
      "supports_stance": false,
      "default_rep_range": [8, 12],
      "default_sets": 3,
      "tags": ["hypertrophy", "isolation"]
    },
    {
      "name": "Dumbbell Curl",
      "aliases": ["DB Curl", "Alternating Curl"],
      "primary_muscles": ["biceps"],
      "secondary_muscles": ["forearms"],
      "equipment": "dumbbell",
      "movement_pattern": "isolation",
      "force_type": "pull",
      "mechanics": "isolation",
      "supports_bodyweight": false,
      "supports_incline": false,
      "supports_grip": false,
      "supports_stance": false,
      "default_rep_range": [10, 15],
      "default_sets": 3,
      "tags": ["hypertrophy", "isolation"]
    },
    {
      "name": "Hammer Curl",
      "aliases": [],
      "primary_muscles": ["biceps", "forearms"],
      "secondary_muscles": [],
      "equipment": "dumbbell",
      "movement_pattern": "isolation",
      "force_type": "pull",
      "mechanics": "isolation",
      "supports_bodyweight": false,
      "supports_incline": false,
      "supports_grip": false,
      "supports_stance": false,
      "default_rep_range": [10, 15],
      "default_sets": 3,
      "tags": ["hypertrophy", "isolation"]
    },
    {
      "name": "Incline Dumbbell Curl",
      "aliases": [],
      "primary_muscles": ["biceps"],
      "secondary_muscles": [],
      "equipment": "dumbbell",
      "movement_pattern": "isolation",
      "force_type": "pull",
      "mechanics": "isolation",
      "supports_bodyweight": false,
      "supports_incline": false,
      "supports_grip": false,
      "supports_stance": false,
      "default_rep_range": [10, 15],
      "default_sets": 3,
      "tags": ["hypertrophy", "isolation"]
    },
    {
      "name": "Preacher Curl",
      "aliases": ["EZ Bar Preacher Curl"],
      "primary_muscles": ["biceps"],
      "secondary_muscles": [],
      "equipment": "barbell",
      "movement_pattern": "isolation",
      "force_type": "pull",
      "mechanics": "isolation",
      "supports_bodyweight": false,
      "supports_incline": false,
      "supports_grip": false,
      "supports_stance": false,
      "default_rep_range": [8, 12],
      "default_sets": 3,
      "tags": ["hypertrophy", "isolation"]
    },
    {
      "name": "Cable Curl",
      "aliases": [],
      "primary_muscles": ["biceps"],
      "secondary_muscles": [],
      "equipment": "cable",
      "movement_pattern": "isolation",
      "force_type": "pull",
      "mechanics": "isolation",
      "supports_bodyweight": false,
      "supports_incline": false,
      "supports_grip": true,
      "supports_stance": false,
      "default_rep_range": [10, 15],
      "default_sets": 3,
      "tags": ["hypertrophy", "isolation"]
    },
    {
      "name": "Concentration Curl",
      "aliases": [],
      "primary_muscles": ["biceps"],
      "secondary_muscles": [],
      "equipment": "dumbbell",
      "movement_pattern": "isolation",
      "force_type": "pull",
      "mechanics": "isolation",
      "supports_bodyweight": false,
      "supports_incline": false,
      "supports_grip": false,
      "supports_stance": false,
      "default_rep_range": [10, 15],
      "default_sets": 3,
      "tags": ["hypertrophy", "isolation"]
    },
    {
      "name": "Close-Grip Bench Press",
      "aliases": ["CGBP"],
      "primary_muscles": ["triceps"],
      "secondary_muscles": ["chest", "anterior_deltoid"],
      "equipment": "barbell",
      "movement_pattern": "isolation",
      "force_type": "push",
      "mechanics": "compound",
      "supports_bodyweight": false,
      "supports_incline": false,
      "supports_grip": false,
      "supports_stance": false,
      "default_rep_range": [6, 10],
      "default_sets": 3,
      "tags": ["strength", "hypertrophy"]
    },
    {
      "name": "Tricep Pushdown",
      "aliases": ["Cable Pushdown", "Tricep Pulldown"],
      "primary_muscles": ["triceps"],
      "secondary_muscles": [],
      "equipment": "cable",
      "movement_pattern": "isolation",
      "force_type": "push",
      "mechanics": "isolation",
      "supports_bodyweight": false,
      "supports_incline": false,
      "supports_grip": true,
      "supports_stance": false,
      "default_rep_range": [10, 15],
      "default_sets": 3,
      "tags": ["hypertrophy", "isolation"]
    },
    {
      "name": "Overhead Tricep Extension",
      "aliases": ["French Press", "DB Skull Crusher"],
      "primary_muscles": ["triceps"],
      "secondary_muscles": [],
      "equipment": "dumbbell",
      "movement_pattern": "isolation",
      "force_type": "push",
      "mechanics": "isolation",
      "supports_bodyweight": false,
      "supports_incline": false,
      "supports_grip": false,
      "supports_stance": false,
      "default_rep_range": [10, 15],
      "default_sets": 3,
      "tags": ["hypertrophy", "isolation"]
    },
    {
      "name": "Skull Crusher",
      "aliases": ["EZ Bar Skull Crusher", "Lying Tricep Extension"],
      "primary_muscles": ["triceps"],
      "secondary_muscles": [],
      "equipment": "barbell",
      "movement_pattern": "isolation",
      "force_type": "push",
      "mechanics": "isolation",
      "supports_bodyweight": false,
      "supports_incline": false,
      "supports_grip": false,
      "supports_stance": false,
      "default_rep_range": [8, 12],
      "default_sets": 3,
      "tags": ["hypertrophy", "isolation"]
    },
    {
      "name": "Tricep Dips",
      "aliases": ["Bench Dips", "Dips (Tricep)"],
      "primary_muscles": ["triceps"],
      "secondary_muscles": ["anterior_deltoid", "chest"],
      "equipment": "bodyweight",
      "movement_pattern": "isolation",
      "force_type": "push",
      "mechanics": "compound",
      "supports_bodyweight": true,
      "supports_incline": false,
      "supports_grip": false,
      "supports_stance": false,
      "default_rep_range": [8, 15],
      "default_sets": 3,
      "tags": ["calisthenics", "hypertrophy"]
    },
    {
      "name": "JM Press",
      "aliases": [],
      "primary_muscles": ["triceps"],
      "secondary_muscles": ["chest"],
      "equipment": "barbell",
      "movement_pattern": "isolation",
      "force_type": "push",
      "mechanics": "isolation",
      "supports_bodyweight": false,
      "supports_incline": false,
      "supports_grip": false,
      "supports_stance": false,
      "default_rep_range": [6, 10],
      "default_sets": 3,
      "tags": ["powerlifting", "hypertrophy"]
    },
    {
      "name": "Cable Overhead Tricep Extension",
      "aliases": [],
      "primary_muscles": ["triceps"],
      "secondary_muscles": [],
      "equipment": "cable",
      "movement_pattern": "isolation",
      "force_type": "push",
      "mechanics": "isolation",
      "supports_bodyweight": false,
      "supports_incline": false,
      "supports_grip": true,
      "supports_stance": false,
      "default_rep_range": [10, 15],
      "default_sets": 3,
      "tags": ["hypertrophy", "isolation"]
    },
    {
      "name": "Diamond Push-Up",
      "aliases": ["Triangle Push-Up"],
      "primary_muscles": ["triceps"],
      "secondary_muscles": ["chest"],
      "equipment": "bodyweight",
      "movement_pattern": "isolation",
      "force_type": "push",
      "mechanics": "isolation",
      "supports_bodyweight": true,
      "supports_incline": false,
      "supports_grip": false,
      "supports_stance": false,
      "default_rep_range": [8, 15],
      "default_sets": 3,
      "tags": ["calisthenics", "hypertrophy"]
    },
    {
      "name": "Leg Extension",
      "aliases": [],
      "primary_muscles": ["quads"],
      "secondary_muscles": [],
      "equipment": "machine",
      "movement_pattern": "isolation",
      "force_type": "push",
      "mechanics": "isolation",
      "supports_bodyweight": false,
      "supports_incline": false,
      "supports_grip": false,
      "supports_stance": false,
      "default_rep_range": [10, 20],
      "default_sets": 3,
      "tags": ["hypertrophy", "isolation"]
    },
    {
      "name": "Lying Leg Curl",
      "aliases": ["Leg Curl"],
      "primary_muscles": ["hamstrings"],
      "secondary_muscles": [],
      "equipment": "machine",
      "movement_pattern": "isolation",
      "force_type": "pull",
      "mechanics": "isolation",
      "supports_bodyweight": false,
      "supports_incline": false,
      "supports_grip": false,
      "supports_stance": false,
      "default_rep_range": [10, 15],
      "default_sets": 3,
      "tags": ["hypertrophy", "isolation"]
    },
    {
      "name": "Seated Leg Curl",
      "aliases": [],
      "primary_muscles": ["hamstrings"],
      "secondary_muscles": [],
      "equipment": "machine",
      "movement_pattern": "isolation",
      "force_type": "pull",
      "mechanics": "isolation",
      "supports_bodyweight": false,
      "supports_incline": false,
      "supports_grip": false,
      "supports_stance": false,
      "default_rep_range": [10, 15],
      "default_sets": 3,
      "tags": ["hypertrophy", "isolation"]
    },
    {
      "name": "Standing Calf Raise",
      "aliases": ["Calf Raise"],
      "primary_muscles": ["calves"],
      "secondary_muscles": [],
      "equipment": "machine",
      "movement_pattern": "isolation",
      "force_type": "push",
      "mechanics": "isolation",
      "supports_bodyweight": true,
      "supports_incline": false,
      "supports_grip": false,
      "supports_stance": false,
      "default_rep_range": [12, 20],
      "default_sets": 4,
      "tags": ["hypertrophy", "isolation"]
    },
    {
      "name": "Seated Calf Raise",
      "aliases": [],
      "primary_muscles": ["calves"],
      "secondary_muscles": [],
      "equipment": "machine",
      "movement_pattern": "isolation",
      "force_type": "push",
      "mechanics": "isolation",
      "supports_bodyweight": false,
      "supports_incline": false,
      "supports_grip": false,
      "supports_stance": false,
      "default_rep_range": [12, 20],
      "default_sets": 4,
      "tags": ["hypertrophy", "isolation"]
    },
    {
      "name": "Hip Abduction Machine",
      "aliases": ["Leg Abduction"],
      "primary_muscles": ["abductors", "glutes"],
      "secondary_muscles": [],
      "equipment": "machine",
      "movement_pattern": "isolation",
      "force_type": "push",
      "mechanics": "isolation",
      "supports_bodyweight": false,
      "supports_incline": false,
      "supports_grip": false,
      "supports_stance": false,
      "default_rep_range": [12, 20],
      "default_sets": 3,
      "tags": ["hypertrophy", "isolation"]
    },
    {
      "name": "Hip Adduction Machine",
      "aliases": ["Leg Adduction"],
      "primary_muscles": ["adductors"],
      "secondary_muscles": [],
      "equipment": "machine",
      "movement_pattern": "isolation",
      "force_type": "pull",
      "mechanics": "isolation",
      "supports_bodyweight": false,
      "supports_incline": false,
      "supports_grip": false,
      "supports_stance": false,
      "default_rep_range": [12, 20],
      "default_sets": 3,
      "tags": ["hypertrophy", "isolation"]
    },
    {
      "name": "Cable Glute Kickback",
      "aliases": ["Glute Kickback"],
      "primary_muscles": ["glutes"],
      "secondary_muscles": ["hamstrings"],
      "equipment": "cable",
      "movement_pattern": "isolation",
      "force_type": "pull",
      "mechanics": "isolation",
      "supports_bodyweight": false,
      "supports_incline": false,
      "supports_grip": false,
      "supports_stance": false,
      "default_rep_range": [12, 20],
      "default_sets": 3,
      "tags": ["hypertrophy", "glute"]
    },
    {
      "name": "Face Pull",
      "aliases": [],
      "primary_muscles": ["rear_deltoid", "traps"],
      "secondary_muscles": ["biceps", "external_rotators"],
      "equipment": "cable",
      "movement_pattern": "isolation",
      "force_type": "pull",
      "mechanics": "isolation",
      "supports_bodyweight": false,
      "supports_incline": false,
      "supports_grip": false,
      "supports_stance": false,
      "default_rep_range": [12, 20],
      "default_sets": 3,
      "tags": ["shoulder-health", "hypertrophy", "prehab"]
    },
    {
      "name": "Rear Delt Flye",
      "aliases": ["Reverse Flye", "Bent-Over Lateral Raise"],
      "primary_muscles": ["rear_deltoid"],
      "secondary_muscles": ["traps"],
      "equipment": "dumbbell",
      "movement_pattern": "isolation",
      "force_type": "pull",
      "mechanics": "isolation",
      "supports_bodyweight": false,
      "supports_incline": false,
      "supports_grip": false,
      "supports_stance": false,
      "default_rep_range": [12, 20],
      "default_sets": 3,
      "tags": ["hypertrophy", "isolation"]
    },
    {
      "name": "Upright Row",
      "aliases": [],
      "primary_muscles": ["traps", "lateral_deltoid"],
      "secondary_muscles": ["biceps"],
      "equipment": "barbell",
      "movement_pattern": "isolation",
      "force_type": "pull",
      "mechanics": "compound",
      "supports_bodyweight": false,
      "supports_incline": false,
      "supports_grip": false,
      "supports_stance": false,
      "default_rep_range": [10, 15],
      "default_sets": 3,
      "tags": ["hypertrophy"]
    },
    {
      "name": "Front Raise",
      "aliases": [],
      "primary_muscles": ["anterior_deltoid"],
      "secondary_muscles": [],
      "equipment": "dumbbell",
      "movement_pattern": "isolation",
      "force_type": "push",
      "mechanics": "isolation",
      "supports_bodyweight": false,
      "supports_incline": false,
      "supports_grip": false,
      "supports_stance": false,
      "default_rep_range": [12, 15],
      "default_sets": 3,
      "tags": ["hypertrophy", "isolation"]
    },
    {
      "name": "Barbell Shrug",
      "aliases": ["Shrug"],
      "primary_muscles": ["traps"],
      "secondary_muscles": [],
      "equipment": "barbell",
      "movement_pattern": "isolation",
      "force_type": "pull",
      "mechanics": "isolation",
      "supports_bodyweight": false,
      "supports_incline": false,
      "supports_grip": false,
      "supports_stance": false,
      "default_rep_range": [10, 15],
      "default_sets": 3,
      "tags": ["hypertrophy", "isolation"]
    },
    {
      "name": "Dumbbell Shrug",
      "aliases": [],
      "primary_muscles": ["traps"],
      "secondary_muscles": [],
      "equipment": "dumbbell",
      "movement_pattern": "isolation",
      "force_type": "pull",
      "mechanics": "isolation",
      "supports_bodyweight": false,
      "supports_incline": false,
      "supports_grip": false,
      "supports_stance": false,
      "default_rep_range": [12, 20],
      "default_sets": 3,
      "tags": ["hypertrophy", "isolation"]
    },
    {
      "name": "Wrist Curl",
      "aliases": [],
      "primary_muscles": ["forearms"],
      "secondary_muscles": [],
      "equipment": "dumbbell",
      "movement_pattern": "isolation",
      "force_type": "pull",
      "mechanics": "isolation",
      "supports_bodyweight": false,
      "supports_incline": false,
      "supports_grip": false,
      "supports_stance": false,
      "default_rep_range": [15, 20],
      "default_sets": 3,
      "tags": ["hypertrophy", "isolation", "grip"]
    },
    {
      "name": "Reverse Wrist Curl",
      "aliases": [],
      "primary_muscles": ["forearms"],
      "secondary_muscles": [],
      "equipment": "barbell",
      "movement_pattern": "isolation",
      "force_type": "push",
      "mechanics": "isolation",
      "supports_bodyweight": false,
      "supports_incline": false,
      "supports_grip": false,
      "supports_stance": false,
      "default_rep_range": [15, 20],
      "default_sets": 3,
      "tags": ["hypertrophy", "isolation", "grip"]
    },

    {"name":"Cable Crossover","aliases":["Cable Cross","Standing Cable Flye"],"primary_muscles":["chest"],"secondary_muscles":["anterior_deltoid","biceps"],"equipment":"cable","movement_pattern":"push_horizontal","force_type":"push","mechanics":"isolation","supports_bodyweight":false,"supports_incline":true,"supports_grip":false,"supports_stance":false,"default_rep_range":[10,15],"default_sets":3,"tags":["hypertrophy","isolation"]},
    {"name":"Cable Woodchop","aliases":["Wood Chop","Cable Chop"],"primary_muscles":["core","abs"],"secondary_muscles":["shoulders","glutes"],"equipment":"cable","movement_pattern":"core","force_type":"pull","mechanics":"compound","supports_bodyweight":false,"supports_incline":false,"supports_grip":false,"supports_stance":false,"default_rep_range":[10,15],"default_sets":3,"tags":["core","functional"]},
    {"name":"Cable Reverse Flye","aliases":["Cable Rear Delt Flye","Reverse Cable Flye"],"primary_muscles":["rear_deltoid"],"secondary_muscles":["traps","back"],"equipment":"cable","movement_pattern":"pull_horizontal","force_type":"pull","mechanics":"isolation","supports_bodyweight":false,"supports_incline":false,"supports_grip":false,"supports_stance":false,"default_rep_range":[12,20],"default_sets":3,"tags":["hypertrophy","isolation","shoulder_health"]},
    {"name":"Cable Front Raise","aliases":["Cable Anterior Raise"],"primary_muscles":["anterior_deltoid"],"secondary_muscles":["lateral_deltoid"],"equipment":"cable","movement_pattern":"push_vertical","force_type":"push","mechanics":"isolation","supports_bodyweight":false,"supports_incline":false,"supports_grip":false,"supports_stance":false,"default_rep_range":[12,15],"default_sets":3,"tags":["hypertrophy","isolation"]},
    {"name":"Cable Upright Row","aliases":[],"primary_muscles":["lateral_deltoid","traps"],"secondary_muscles":["biceps","anterior_deltoid"],"equipment":"cable","movement_pattern":"pull_vertical","force_type":"pull","mechanics":"compound","supports_bodyweight":false,"supports_incline":false,"supports_grip":true,"supports_stance":false,"default_rep_range":[10,15],"default_sets":3,"tags":["hypertrophy"]},
    {"name":"Cable Tricep Kickback","aliases":["Cable Kickback"],"primary_muscles":["triceps"],"secondary_muscles":[],"equipment":"cable","movement_pattern":"isolation","force_type":"push","mechanics":"isolation","supports_bodyweight":false,"supports_incline":false,"supports_grip":false,"supports_stance":false,"default_rep_range":[12,15],"default_sets":3,"tags":["hypertrophy","isolation"]},
    {"name":"Cable Hammer Curl","aliases":["Rope Hammer Curl"],"primary_muscles":["biceps","forearms"],"secondary_muscles":[],"equipment":"cable","movement_pattern":"isolation","force_type":"pull","mechanics":"isolation","supports_bodyweight":false,"supports_incline":false,"supports_grip":true,"supports_stance":false,"default_rep_range":[10,15],"default_sets":3,"tags":["hypertrophy","isolation"]},
    {"name":"Cable Pull-Through","aliases":["Pull Through"],"primary_muscles":["glutes","hamstrings"],"secondary_muscles":["erectors"],"equipment":"cable","movement_pattern":"hinge","force_type":"pull","mechanics":"compound","supports_bodyweight":false,"supports_incline":false,"supports_grip":false,"supports_stance":false,"default_rep_range":[10,15],"default_sets":3,"tags":["hypertrophy","glute_activation"]},
    {"name":"Cable Hip Abduction","aliases":["Standing Cable Abduction"],"primary_muscles":["abductors","glutes"],"secondary_muscles":[],"equipment":"cable","movement_pattern":"isolation","force_type":"push","mechanics":"isolation","supports_bodyweight":false,"supports_incline":false,"supports_grip":false,"supports_stance":false,"default_rep_range":[12,20],"default_sets":3,"tags":["hypertrophy","isolation","unilateral"]},
    {"name":"Cable Reverse Curl","aliases":[],"primary_muscles":["forearms","biceps"],"secondary_muscles":[],"equipment":"cable","movement_pattern":"isolation","force_type":"pull","mechanics":"isolation","supports_bodyweight":false,"supports_incline":false,"supports_grip":false,"supports_stance":false,"default_rep_range":[12,15],"default_sets":3,"tags":["hypertrophy","isolation"]},
    {"name":"Cable Shrug","aliases":[],"primary_muscles":["traps"],"secondary_muscles":["shoulders"],"equipment":"cable","movement_pattern":"isolation","force_type":"pull","mechanics":"isolation","supports_bodyweight":false,"supports_incline":false,"supports_grip":false,"supports_stance":false,"default_rep_range":[10,15],"default_sets":3,"tags":["hypertrophy","isolation"]},
    {"name":"Cable Wrist Curl","aliases":[],"primary_muscles":["forearms"],"secondary_muscles":[],"equipment":"cable","movement_pattern":"isolation","force_type":"pull","mechanics":"isolation","supports_bodyweight":false,"supports_incline":false,"supports_grip":false,"supports_stance":false,"default_rep_range":[15,20],"default_sets":3,"tags":["hypertrophy","isolation"]},
    {"name":"Cable External Rotation","aliases":["Cable ER"],"primary_muscles":["rear_deltoid"],"secondary_muscles":["shoulders"],"equipment":"cable","movement_pattern":"isolation","force_type":"pull","mechanics":"isolation","supports_bodyweight":false,"supports_incline":false,"supports_grip":false,"supports_stance":false,"default_rep_range":[15,20],"default_sets":3,"tags":["prehab","shoulder_health"]},
    {"name":"Cable Internal Rotation","aliases":["Cable IR"],"primary_muscles":["anterior_deltoid"],"secondary_muscles":["shoulders"],"equipment":"cable","movement_pattern":"isolation","force_type":"push","mechanics":"isolation","supports_bodyweight":false,"supports_incline":false,"supports_grip":false,"supports_stance":false,"default_rep_range":[15,20],"default_sets":3,"tags":["prehab","shoulder_health"]},
    {"name":"Single-Arm Cable Chest Flye","aliases":["One-Arm Cable Flye"],"primary_muscles":["chest"],"secondary_muscles":["anterior_deltoid"],"equipment":"cable","movement_pattern":"push_horizontal","force_type":"push","mechanics":"isolation","supports_bodyweight":false,"supports_incline":true,"supports_grip":false,"supports_stance":false,"default_rep_range":[10,15],"default_sets":3,"tags":["hypertrophy","isolation","unilateral"]},
    {"name":"Cable Bayesian Curl","aliases":["Bayesian Curl"],"primary_muscles":["biceps"],"secondary_muscles":[],"equipment":"cable","movement_pattern":"isolation","force_type":"pull","mechanics":"isolation","supports_bodyweight":false,"supports_incline":false,"supports_grip":false,"supports_stance":false,"default_rep_range":[10,15],"default_sets":3,"tags":["hypertrophy","isolation"]},

    {"name":"Ring Dip","aliases":["Rings Dip","Gymnastic Ring Dip"],"primary_muscles":["chest","triceps"],"secondary_muscles":["anterior_deltoid","core"],"equipment":"bodyweight","movement_pattern":"push_horizontal","force_type":"push","mechanics":"compound","supports_bodyweight":true,"supports_incline":false,"supports_grip":false,"supports_stance":false,"default_rep_range":[5,12],"default_sets":3,"tags":["calisthenics","strength","rings"]},
    {"name":"Ring Push-Up","aliases":["Rings Push-Up"],"primary_muscles":["chest","triceps"],"secondary_muscles":["anterior_deltoid","core"],"equipment":"bodyweight","movement_pattern":"push_horizontal","force_type":"push","mechanics":"compound","supports_bodyweight":true,"supports_incline":false,"supports_grip":false,"supports_stance":false,"default_rep_range":[8,15],"default_sets":3,"tags":["calisthenics","rings"]},
    {"name":"Ring Row","aliases":["Ring Inverted Row","Rings Row"],"primary_muscles":["back","lats"],"secondary_muscles":["biceps","rear_deltoid","core"],"equipment":"bodyweight","movement_pattern":"pull_horizontal","force_type":"pull","mechanics":"compound","supports_bodyweight":true,"supports_incline":false,"supports_grip":true,"supports_stance":false,"default_rep_range":[8,15],"default_sets":3,"tags":["calisthenics","rings"]},
    {"name":"Ring Muscle-Up","aliases":["Rings Muscle-Up"],"primary_muscles":["lats","chest","triceps"],"secondary_muscles":["biceps","core","anterior_deltoid"],"equipment":"bodyweight","movement_pattern":"pull_vertical","force_type":"pull","mechanics":"compound","supports_bodyweight":true,"supports_incline":false,"supports_grip":false,"supports_stance":false,"default_rep_range":[1,5],"default_sets":3,"tags":["calisthenics","strength","rings","advanced"]},
    {"name":"Ring Face Pull","aliases":["Rings Face Pull"],"primary_muscles":["rear_deltoid","traps"],"secondary_muscles":["biceps","back"],"equipment":"bodyweight","movement_pattern":"pull_horizontal","force_type":"pull","mechanics":"compound","supports_bodyweight":true,"supports_incline":false,"supports_grip":false,"supports_stance":false,"default_rep_range":[10,15],"default_sets":3,"tags":["calisthenics","rings","shoulder_health"]},
    {"name":"Ring L-Sit","aliases":["Rings L-Sit"],"primary_muscles":["abs","hip_flexors"],"secondary_muscles":["triceps","core"],"equipment":"bodyweight","movement_pattern":"core","force_type":"static","mechanics":"compound","supports_bodyweight":true,"supports_incline":false,"supports_grip":false,"supports_stance":false,"default_rep_range":[5,10],"default_sets":3,"tags":["calisthenics","rings","isometric"]},
    {"name":"Ring Flye","aliases":["Rings Flye","Ring Chest Flye"],"primary_muscles":["chest"],"secondary_muscles":["anterior_deltoid","biceps","core"],"equipment":"bodyweight","movement_pattern":"push_horizontal","force_type":"push","mechanics":"isolation","supports_bodyweight":true,"supports_incline":false,"supports_grip":false,"supports_stance":false,"default_rep_range":[6,12],"default_sets":3,"tags":["calisthenics","rings","advanced"]},
    {"name":"Ring Rollout","aliases":["Rings Ab Rollout"],"primary_muscles":["abs","core"],"secondary_muscles":["lats","triceps"],"equipment":"bodyweight","movement_pattern":"core","force_type":"push","mechanics":"compound","supports_bodyweight":true,"supports_incline":false,"supports_grip":false,"supports_stance":false,"default_rep_range":[6,12],"default_sets":3,"tags":["calisthenics","rings","core"]},
    {"name":"Ring Tricep Extension","aliases":["Ring Skull Crusher","Rings Tricep Extension"],"primary_muscles":["triceps"],"secondary_muscles":["core"],"equipment":"bodyweight","movement_pattern":"isolation","force_type":"push","mechanics":"isolation","supports_bodyweight":true,"supports_incline":false,"supports_grip":false,"supports_stance":false,"default_rep_range":[8,15],"default_sets":3,"tags":["calisthenics","rings"]},
    {"name":"Ring Curl","aliases":["Ring Bicep Curl","Rings Curl"],"primary_muscles":["biceps"],"secondary_muscles":["forearms","core"],"equipment":"bodyweight","movement_pattern":"isolation","force_type":"pull","mechanics":"isolation","supports_bodyweight":true,"supports_incline":false,"supports_grip":false,"supports_stance":false,"default_rep_range":[8,15],"default_sets":3,"tags":["calisthenics","rings"]},
    {"name":"Ring Pike Push-Up","aliases":["Rings Pike Press"],"primary_muscles":["shoulders","anterior_deltoid"],"secondary_muscles":["triceps","core"],"equipment":"bodyweight","movement_pattern":"push_vertical","force_type":"push","mechanics":"compound","supports_bodyweight":true,"supports_incline":false,"supports_grip":false,"supports_stance":false,"default_rep_range":[5,10],"default_sets":3,"tags":["calisthenics","rings"]},
    {"name":"Ring Archer Push-Up","aliases":["Rings Archer Push-Up"],"primary_muscles":["chest","triceps"],"secondary_muscles":["anterior_deltoid","core"],"equipment":"bodyweight","movement_pattern":"push_horizontal","force_type":"push","mechanics":"compound","supports_bodyweight":true,"supports_incline":false,"supports_grip":false,"supports_stance":false,"default_rep_range":[4,8],"default_sets":3,"tags":["calisthenics","rings","advanced","unilateral"]},

    {"name":"Turkish Get-Up","aliases":["TGU","Kettlebell Get-Up"],"primary_muscles":["shoulders","core","glutes"],"secondary_muscles":["triceps","hip_flexors","quads"],"equipment":"kettlebell","movement_pattern":"core","force_type":"push","mechanics":"compound","supports_bodyweight":false,"supports_incline":false,"supports_grip":false,"supports_stance":false,"default_rep_range":[1,3],"default_sets":3,"tags":["functional","strength","stability"]},
    {"name":"Kettlebell Clean & Press","aliases":["KB Clean and Press"],"primary_muscles":["shoulders","glutes"],"secondary_muscles":["triceps","core","hamstrings"],"equipment":"kettlebell","movement_pattern":"push_vertical","force_type":"push","mechanics":"compound","supports_bodyweight":false,"supports_incline":false,"supports_grip":false,"supports_stance":false,"default_rep_range":[5,8],"default_sets":3,"tags":["functional","strength"]},
    {"name":"Kettlebell Snatch","aliases":["KB Snatch"],"primary_muscles":["shoulders","glutes","hamstrings"],"secondary_muscles":["core","traps","forearms"],"equipment":"kettlebell","movement_pattern":"hinge","force_type":"push","mechanics":"compound","supports_bodyweight":false,"supports_incline":false,"supports_grip":false,"supports_stance":false,"default_rep_range":[5,10],"default_sets":3,"tags":["functional","power","conditioning"]},
    {"name":"Kettlebell Windmill","aliases":["KB Windmill"],"primary_muscles":["core","shoulders"],"secondary_muscles":["hamstrings","glutes","hip_flexors"],"equipment":"kettlebell","movement_pattern":"core","force_type":"static","mechanics":"compound","supports_bodyweight":false,"supports_incline":false,"supports_grip":false,"supports_stance":false,"default_rep_range":[5,8],"default_sets":3,"tags":["functional","mobility","stability"]},
    {"name":"Kettlebell Row","aliases":["KB Row","Single-Arm Kettlebell Row"],"primary_muscles":["lats","back"],"secondary_muscles":["biceps","rear_deltoid","core"],"equipment":"kettlebell","movement_pattern":"pull_horizontal","force_type":"pull","mechanics":"compound","supports_bodyweight":false,"supports_incline":false,"supports_grip":false,"supports_stance":false,"default_rep_range":[8,12],"default_sets":3,"tags":["strength","hypertrophy","unilateral"]},
    {"name":"Kettlebell Deadlift","aliases":["KB Deadlift"],"primary_muscles":["glutes","hamstrings"],"secondary_muscles":["erectors","quads","forearms"],"equipment":"kettlebell","movement_pattern":"hinge","force_type":"pull","mechanics":"compound","supports_bodyweight":false,"supports_incline":false,"supports_grip":false,"supports_stance":true,"default_rep_range":[8,12],"default_sets":3,"tags":["strength","beginner"]},
    {"name":"Kettlebell Goblet Squat","aliases":["KB Goblet Squat"],"primary_muscles":["quads","glutes"],"secondary_muscles":["core","adductors"],"equipment":"kettlebell","movement_pattern":"squat","force_type":"push","mechanics":"compound","supports_bodyweight":false,"supports_incline":false,"supports_grip":false,"supports_stance":true,"default_rep_range":[8,15],"default_sets":3,"tags":["hypertrophy","beginner"]},
    {"name":"Kettlebell Halo","aliases":["KB Halo"],"primary_muscles":["shoulders"],"secondary_muscles":["core","triceps"],"equipment":"kettlebell","movement_pattern":"isolation","force_type":"push","mechanics":"compound","supports_bodyweight":false,"supports_incline":false,"supports_grip":false,"supports_stance":false,"default_rep_range":[8,12],"default_sets":3,"tags":["warmup","mobility","shoulder_health"]},
    {"name":"Kettlebell Thruster","aliases":["KB Thruster"],"primary_muscles":["quads","glutes","shoulders"],"secondary_muscles":["triceps","core"],"equipment":"kettlebell","movement_pattern":"push_vertical","force_type":"push","mechanics":"compound","supports_bodyweight":false,"supports_incline":false,"supports_grip":false,"supports_stance":false,"default_rep_range":[8,12],"default_sets":3,"tags":["functional","conditioning"]},

    {"name":"Band Pull-Apart","aliases":["Banded Pull-Apart"],"primary_muscles":["rear_deltoid","traps"],"secondary_muscles":["back"],"equipment":"band","movement_pattern":"pull_horizontal","force_type":"pull","mechanics":"isolation","supports_bodyweight":false,"supports_incline":false,"supports_grip":false,"supports_stance":false,"default_rep_range":[15,25],"default_sets":3,"tags":["prehab","warmup","shoulder_health"]},
    {"name":"Band Face Pull","aliases":["Banded Face Pull"],"primary_muscles":["rear_deltoid","traps"],"secondary_muscles":["biceps","back"],"equipment":"band","movement_pattern":"pull_horizontal","force_type":"pull","mechanics":"compound","supports_bodyweight":false,"supports_incline":false,"supports_grip":false,"supports_stance":false,"default_rep_range":[15,20],"default_sets":3,"tags":["prehab","warmup","shoulder_health"]},
    {"name":"Band Good Morning","aliases":["Banded Good Morning"],"primary_muscles":["hamstrings","glutes"],"secondary_muscles":["erectors"],"equipment":"band","movement_pattern":"hinge","force_type":"pull","mechanics":"compound","supports_bodyweight":false,"supports_incline":false,"supports_grip":false,"supports_stance":false,"default_rep_range":[12,20],"default_sets":3,"tags":["prehab","warmup"]},
    {"name":"Band Lateral Walk","aliases":["Banded Lateral Walk","Monster Walk"],"primary_muscles":["abductors","glutes"],"secondary_muscles":[],"equipment":"band","movement_pattern":"isolation","force_type":"push","mechanics":"isolation","supports_bodyweight":false,"supports_incline":false,"supports_grip":false,"supports_stance":false,"default_rep_range":[12,20],"default_sets":3,"tags":["prehab","warmup","glute_activation"]},
    {"name":"Band Hip Thrust","aliases":["Banded Hip Thrust"],"primary_muscles":["glutes"],"secondary_muscles":["hamstrings"],"equipment":"band","movement_pattern":"hinge","force_type":"push","mechanics":"compound","supports_bodyweight":false,"supports_incline":false,"supports_grip":false,"supports_stance":false,"default_rep_range":[12,20],"default_sets":3,"tags":["glute_activation","warmup"]},
    {"name":"Band Dislocate","aliases":["Banded Shoulder Dislocate","Band Pass-Through"],"primary_muscles":["shoulders"],"secondary_muscles":["rear_deltoid","chest"],"equipment":"band","movement_pattern":"isolation","force_type":"push","mechanics":"isolation","supports_bodyweight":false,"supports_incline":false,"supports_grip":false,"supports_stance":false,"default_rep_range":[10,15],"default_sets":3,"tags":["warmup","mobility","shoulder_health"]},
    {"name":"Band Tricep Pushdown","aliases":["Banded Pushdown"],"primary_muscles":["triceps"],"secondary_muscles":[],"equipment":"band","movement_pattern":"isolation","force_type":"push","mechanics":"isolation","supports_bodyweight":false,"supports_incline":false,"supports_grip":false,"supports_stance":false,"default_rep_range":[15,25],"default_sets":3,"tags":["hypertrophy","isolation"]},
    {"name":"Band Curl","aliases":["Banded Curl"],"primary_muscles":["biceps"],"secondary_muscles":["forearms"],"equipment":"band","movement_pattern":"isolation","force_type":"pull","mechanics":"isolation","supports_bodyweight":false,"supports_incline":false,"supports_grip":false,"supports_stance":false,"default_rep_range":[15,25],"default_sets":3,"tags":["hypertrophy","isolation"]},

    {"name":"Inverted Row","aliases":["Body Row","Australian Pull-Up"],"primary_muscles":["back","lats"],"secondary_muscles":["biceps","rear_deltoid","core"],"equipment":"bodyweight","movement_pattern":"pull_horizontal","force_type":"pull","mechanics":"compound","supports_bodyweight":true,"supports_incline":false,"supports_grip":true,"supports_stance":false,"default_rep_range":[8,15],"default_sets":3,"tags":["calisthenics","beginner"]},
    {"name":"Muscle-Up","aliases":["Bar Muscle-Up"],"primary_muscles":["lats","chest","triceps"],"secondary_muscles":["biceps","core","anterior_deltoid"],"equipment":"bodyweight","movement_pattern":"pull_vertical","force_type":"pull","mechanics":"compound","supports_bodyweight":true,"supports_incline":false,"supports_grip":false,"supports_stance":false,"default_rep_range":[1,5],"default_sets":3,"tags":["calisthenics","strength","advanced"]},
    {"name":"Pistol Squat","aliases":["Single-Leg Squat"],"primary_muscles":["quads","glutes"],"secondary_muscles":["hamstrings","core","hip_flexors"],"equipment":"bodyweight","movement_pattern":"squat","force_type":"push","mechanics":"compound","supports_bodyweight":true,"supports_incline":false,"supports_grip":false,"supports_stance":false,"default_rep_range":[3,8],"default_sets":3,"tags":["calisthenics","unilateral","advanced"]},
    {"name":"Bodyweight Squat","aliases":["Air Squat"],"primary_muscles":["quads","glutes"],"secondary_muscles":["hamstrings","adductors"],"equipment":"bodyweight","movement_pattern":"squat","force_type":"push","mechanics":"compound","supports_bodyweight":true,"supports_incline":false,"supports_grip":false,"supports_stance":true,"default_rep_range":[15,25],"default_sets":3,"tags":["calisthenics","beginner","warmup"]},
    {"name":"Step-Up","aliases":["Box Step-Up"],"primary_muscles":["quads","glutes"],"secondary_muscles":["hamstrings"],"equipment":"bodyweight","movement_pattern":"squat","force_type":"push","mechanics":"compound","supports_bodyweight":true,"supports_incline":false,"supports_grip":false,"supports_stance":false,"default_rep_range":[8,15],"default_sets":3,"tags":["unilateral","beginner"]},
    {"name":"Glute Bridge","aliases":["Floor Hip Thrust"],"primary_muscles":["glutes"],"secondary_muscles":["hamstrings","core"],"equipment":"bodyweight","movement_pattern":"hinge","force_type":"push","mechanics":"compound","supports_bodyweight":true,"supports_incline":false,"supports_grip":false,"supports_stance":false,"default_rep_range":[12,20],"default_sets":3,"tags":["glute_activation","beginner"]},
    {"name":"Bodyweight Calf Raise","aliases":["Single-Leg Calf Raise"],"primary_muscles":["calves"],"secondary_muscles":[],"equipment":"bodyweight","movement_pattern":"isolation","force_type":"push","mechanics":"isolation","supports_bodyweight":true,"supports_incline":false,"supports_grip":false,"supports_stance":false,"default_rep_range":[15,25],"default_sets":3,"tags":["calisthenics","isolation"]},
    {"name":"Decline Push-Up","aliases":["Feet-Elevated Push-Up"],"primary_muscles":["chest","anterior_deltoid"],"secondary_muscles":["triceps","core"],"equipment":"bodyweight","movement_pattern":"push_horizontal","force_type":"push","mechanics":"compound","supports_bodyweight":true,"supports_incline":false,"supports_grip":false,"supports_stance":false,"default_rep_range":[8,15],"default_sets":3,"tags":["calisthenics"]},
    {"name":"Pike Push-Up","aliases":["Pike Press"],"primary_muscles":["shoulders","anterior_deltoid"],"secondary_muscles":["triceps","core"],"equipment":"bodyweight","movement_pattern":"push_vertical","force_type":"push","mechanics":"compound","supports_bodyweight":true,"supports_incline":false,"supports_grip":false,"supports_stance":false,"default_rep_range":[6,12],"default_sets":3,"tags":["calisthenics"]},
    {"name":"Handstand Push-Up","aliases":["HSPU"],"primary_muscles":["shoulders","anterior_deltoid"],"secondary_muscles":["triceps","traps","core"],"equipment":"bodyweight","movement_pattern":"push_vertical","force_type":"push","mechanics":"compound","supports_bodyweight":true,"supports_incline":false,"supports_grip":false,"supports_stance":false,"default_rep_range":[3,8],"default_sets":3,"tags":["calisthenics","strength","advanced"]},
    {"name":"Bodyweight Lunge","aliases":["Walking Lunge"],"primary_muscles":["quads","glutes"],"secondary_muscles":["hamstrings","adductors"],"equipment":"bodyweight","movement_pattern":"squat","force_type":"push","mechanics":"compound","supports_bodyweight":true,"supports_incline":false,"supports_grip":false,"supports_stance":false,"default_rep_range":[10,15],"default_sets":3,"tags":["calisthenics","beginner","unilateral"]},
    {"name":"Box Jump","aliases":["Plyo Box Jump"],"primary_muscles":["quads","glutes"],"secondary_muscles":["calves","hamstrings"],"equipment":"bodyweight","movement_pattern":"squat","force_type":"push","mechanics":"compound","supports_bodyweight":true,"supports_incline":false,"supports_grip":false,"supports_stance":false,"default_rep_range":[3,6],"default_sets":3,"tags":["plyometric","power"]},
    {"name":"Burpee","aliases":[],"primary_muscles":["chest","quads"],"secondary_muscles":["shoulders","triceps","core","glutes"],"equipment":"bodyweight","movement_pattern":"push_horizontal","force_type":"push","mechanics":"compound","supports_bodyweight":true,"supports_incline":false,"supports_grip":false,"supports_stance":false,"default_rep_range":[8,15],"default_sets":3,"tags":["conditioning","full_body"]},
    {"name":"Mountain Climber","aliases":[],"primary_muscles":["core","hip_flexors"],"secondary_muscles":["quads","shoulders"],"equipment":"bodyweight","movement_pattern":"core","force_type":"push","mechanics":"compound","supports_bodyweight":true,"supports_incline":false,"supports_grip":false,"supports_stance":false,"default_rep_range":[15,25],"default_sets":3,"tags":["conditioning","core"]},
    {"name":"Toes-to-Bar","aliases":["TTB","Toes to Bar"],"primary_muscles":["abs","hip_flexors"],"secondary_muscles":["lats","forearms"],"equipment":"bodyweight","movement_pattern":"core","force_type":"pull","mechanics":"compound","supports_bodyweight":true,"supports_incline":false,"supports_grip":false,"supports_stance":false,"default_rep_range":[5,12],"default_sets":3,"tags":["calisthenics","core"]},
    {"name":"Hollow Body Hold","aliases":["Hollow Hold"],"primary_muscles":["abs","core"],"secondary_muscles":["hip_flexors"],"equipment":"bodyweight","movement_pattern":"core","force_type":"static","mechanics":"isolation","supports_bodyweight":true,"supports_incline":false,"supports_grip":false,"supports_stance":false,"default_rep_range":[5,10],"default_sets":3,"tags":["calisthenics","core","isometric"]},
    {"name":"Superman Hold","aliases":["Back Extension Hold"],"primary_muscles":["erectors"],"secondary_muscles":["glutes","rear_deltoid"],"equipment":"bodyweight","movement_pattern":"core","force_type":"static","mechanics":"isolation","supports_bodyweight":true,"supports_incline":false,"supports_grip":false,"supports_stance":false,"default_rep_range":[5,10],"default_sets":3,"tags":["core","prehab"]},

    {"name":"Reverse Pec Deck","aliases":["Machine Reverse Flye","Rear Delt Machine"],"primary_muscles":["rear_deltoid"],"secondary_muscles":["traps","back"],"equipment":"machine","movement_pattern":"pull_horizontal","force_type":"pull","mechanics":"isolation","supports_bodyweight":false,"supports_incline":false,"supports_grip":false,"supports_stance":false,"default_rep_range":[12,20],"default_sets":3,"tags":["hypertrophy","isolation","shoulder_health"]},
    {"name":"Glute Ham Raise","aliases":["GHR","GHD Raise"],"primary_muscles":["hamstrings","glutes"],"secondary_muscles":["erectors","calves"],"equipment":"machine","movement_pattern":"hinge","force_type":"pull","mechanics":"compound","supports_bodyweight":false,"supports_incline":false,"supports_grip":false,"supports_stance":false,"default_rep_range":[6,12],"default_sets":3,"tags":["strength","hypertrophy"]},
    {"name":"Back Extension","aliases":["Hyperextension","45 Back Extension"],"primary_muscles":["erectors","glutes"],"secondary_muscles":["hamstrings"],"equipment":"machine","movement_pattern":"hinge","force_type":"pull","mechanics":"compound","supports_bodyweight":false,"supports_incline":false,"supports_grip":false,"supports_stance":false,"default_rep_range":[10,15],"default_sets":3,"tags":["hypertrophy","prehab"]},
    {"name":"Leg Press Calf Raise","aliases":["Calf Raise on Leg Press"],"primary_muscles":["calves"],"secondary_muscles":[],"equipment":"machine","movement_pattern":"isolation","force_type":"push","mechanics":"isolation","supports_bodyweight":false,"supports_incline":false,"supports_grip":false,"supports_stance":false,"default_rep_range":[12,20],"default_sets":3,"tags":["hypertrophy","isolation"]},
    {"name":"Machine Preacher Curl","aliases":["Preacher Curl Machine"],"primary_muscles":["biceps"],"secondary_muscles":["forearms"],"equipment":"machine","movement_pattern":"isolation","force_type":"pull","mechanics":"isolation","supports_bodyweight":false,"supports_incline":false,"supports_grip":false,"supports_stance":false,"default_rep_range":[10,15],"default_sets":3,"tags":["hypertrophy","isolation"]},
    {"name":"Machine Tricep Extension","aliases":["Tricep Extension Machine"],"primary_muscles":["triceps"],"secondary_muscles":[],"equipment":"machine","movement_pattern":"isolation","force_type":"push","mechanics":"isolation","supports_bodyweight":false,"supports_incline":false,"supports_grip":false,"supports_stance":false,"default_rep_range":[10,15],"default_sets":3,"tags":["hypertrophy","isolation"]},
    {"name":"Smith Machine Squat","aliases":["Smith Squat"],"primary_muscles":["quads","glutes"],"secondary_muscles":["hamstrings"],"equipment":"machine","movement_pattern":"squat","force_type":"push","mechanics":"compound","supports_bodyweight":false,"supports_incline":false,"supports_grip":false,"supports_stance":true,"default_rep_range":[8,12],"default_sets":3,"tags":["hypertrophy"]},
    {"name":"Smith Machine Bench Press","aliases":["Smith Bench"],"primary_muscles":["chest"],"secondary_muscles":["triceps","anterior_deltoid"],"equipment":"machine","movement_pattern":"push_horizontal","force_type":"push","mechanics":"compound","supports_bodyweight":false,"supports_incline":true,"supports_grip":false,"supports_stance":false,"default_rep_range":[8,12],"default_sets":3,"tags":["hypertrophy"]},
    {"name":"Pendulum Squat","aliases":[],"primary_muscles":["quads"],"secondary_muscles":["glutes"],"equipment":"machine","movement_pattern":"squat","force_type":"push","mechanics":"compound","supports_bodyweight":false,"supports_incline":false,"supports_grip":false,"supports_stance":true,"default_rep_range":[8,15],"default_sets":3,"tags":["hypertrophy"]},
    {"name":"Sissy Squat","aliases":["Sissy Squat Machine"],"primary_muscles":["quads"],"secondary_muscles":["hip_flexors"],"equipment":"machine","movement_pattern":"squat","force_type":"push","mechanics":"isolation","supports_bodyweight":false,"supports_incline":false,"supports_grip":false,"supports_stance":false,"default_rep_range":[8,15],"default_sets":3,"tags":["hypertrophy","isolation"]},

    {"name":"Dumbbell Lunge","aliases":["DB Lunge","Walking Dumbbell Lunge"],"primary_muscles":["quads","glutes"],"secondary_muscles":["hamstrings","adductors"],"equipment":"dumbbell","movement_pattern":"squat","force_type":"push","mechanics":"compound","supports_bodyweight":false,"supports_incline":false,"supports_grip":false,"supports_stance":false,"default_rep_range":[8,12],"default_sets":3,"tags":["hypertrophy","unilateral"]},
    {"name":"Dumbbell Pullover","aliases":["DB Pullover"],"primary_muscles":["lats","chest"],"secondary_muscles":["triceps","serratus"],"equipment":"dumbbell","movement_pattern":"pull_vertical","force_type":"pull","mechanics":"compound","supports_bodyweight":false,"supports_incline":false,"supports_grip":false,"supports_stance":false,"default_rep_range":[10,15],"default_sets":3,"tags":["hypertrophy"]},
    {"name":"Dumbbell Flye","aliases":["DB Flye","Flat Dumbbell Flye"],"primary_muscles":["chest"],"secondary_muscles":["anterior_deltoid"],"equipment":"dumbbell","movement_pattern":"push_horizontal","force_type":"push","mechanics":"isolation","supports_bodyweight":false,"supports_incline":true,"supports_grip":false,"supports_stance":false,"default_rep_range":[10,15],"default_sets":3,"tags":["hypertrophy","isolation"]},
    {"name":"Decline Dumbbell Press","aliases":["Decline DB Press"],"primary_muscles":["chest"],"secondary_muscles":["triceps","anterior_deltoid"],"equipment":"dumbbell","movement_pattern":"push_horizontal","force_type":"push","mechanics":"compound","supports_bodyweight":false,"supports_incline":false,"supports_grip":false,"supports_stance":false,"default_rep_range":[8,12],"default_sets":3,"tags":["hypertrophy"]},
    {"name":"Dumbbell Floor Press","aliases":["DB Floor Press"],"primary_muscles":["chest","triceps"],"secondary_muscles":["anterior_deltoid"],"equipment":"dumbbell","movement_pattern":"push_horizontal","force_type":"push","mechanics":"compound","supports_bodyweight":false,"supports_incline":false,"supports_grip":false,"supports_stance":false,"default_rep_range":[8,12],"default_sets":3,"tags":["strength","hypertrophy"]},
    {"name":"Dumbbell Kickback","aliases":["Tricep Kickback","DB Kickback"],"primary_muscles":["triceps"],"secondary_muscles":[],"equipment":"dumbbell","movement_pattern":"isolation","force_type":"push","mechanics":"isolation","supports_bodyweight":false,"supports_incline":false,"supports_grip":false,"supports_stance":false,"default_rep_range":[12,15],"default_sets":3,"tags":["hypertrophy","isolation"]},
    {"name":"Zottman Curl","aliases":["Zottman Dumbbell Curl"],"primary_muscles":["biceps","forearms"],"secondary_muscles":[],"equipment":"dumbbell","movement_pattern":"isolation","force_type":"pull","mechanics":"isolation","supports_bodyweight":false,"supports_incline":false,"supports_grip":false,"supports_stance":false,"default_rep_range":[8,12],"default_sets":3,"tags":["hypertrophy","isolation"]},
    {"name":"Spider Curl","aliases":["Incline Spider Curl"],"primary_muscles":["biceps"],"secondary_muscles":[],"equipment":"dumbbell","movement_pattern":"isolation","force_type":"pull","mechanics":"isolation","supports_bodyweight":false,"supports_incline":false,"supports_grip":false,"supports_stance":false,"default_rep_range":[10,15],"default_sets":3,"tags":["hypertrophy","isolation"]},
    {"name":"Dumbbell Step-Up","aliases":["DB Step-Up","Weighted Step-Up"],"primary_muscles":["quads","glutes"],"secondary_muscles":["hamstrings"],"equipment":"dumbbell","movement_pattern":"squat","force_type":"push","mechanics":"compound","supports_bodyweight":false,"supports_incline":false,"supports_grip":false,"supports_stance":false,"default_rep_range":[8,12],"default_sets":3,"tags":["hypertrophy","unilateral"]},
    {"name":"Dumbbell Lateral Lunge","aliases":["DB Lateral Lunge","Cossack Squat"],"primary_muscles":["quads","adductors"],"secondary_muscles":["glutes","hamstrings"],"equipment":"dumbbell","movement_pattern":"squat","force_type":"push","mechanics":"compound","supports_bodyweight":false,"supports_incline":false,"supports_grip":false,"supports_stance":false,"default_rep_range":[8,12],"default_sets":3,"tags":["hypertrophy","mobility","unilateral"]},

    {"name":"Barbell Lunge","aliases":["BB Lunge"],"primary_muscles":["quads","glutes"],"secondary_muscles":["hamstrings","adductors","core"],"equipment":"barbell","movement_pattern":"squat","force_type":"push","mechanics":"compound","supports_bodyweight":false,"supports_incline":false,"supports_grip":false,"supports_stance":false,"default_rep_range":[6,10],"default_sets":3,"tags":["strength","hypertrophy","unilateral"]},
    {"name":"Floor Press","aliases":["Barbell Floor Press"],"primary_muscles":["chest","triceps"],"secondary_muscles":["anterior_deltoid"],"equipment":"barbell","movement_pattern":"push_horizontal","force_type":"push","mechanics":"compound","supports_bodyweight":false,"supports_incline":false,"supports_grip":true,"supports_stance":false,"default_rep_range":[5,8],"default_sets":3,"tags":["strength","powerlifting"]},
    {"name":"Pin Press","aliases":["Rack Press","Dead Bench"],"primary_muscles":["chest","triceps"],"secondary_muscles":["anterior_deltoid"],"equipment":"barbell","movement_pattern":"push_horizontal","force_type":"push","mechanics":"compound","supports_bodyweight":false,"supports_incline":false,"supports_grip":true,"supports_stance":false,"default_rep_range":[3,6],"default_sets":3,"tags":["strength","powerlifting"]},
    {"name":"Rack Pull","aliases":["Block Pull"],"primary_muscles":["back","glutes","hamstrings"],"secondary_muscles":["traps","forearms","erectors"],"equipment":"barbell","movement_pattern":"hinge","force_type":"pull","mechanics":"compound","supports_bodyweight":false,"supports_incline":false,"supports_grip":true,"supports_stance":false,"default_rep_range":[3,6],"default_sets":3,"tags":["strength","powerlifting"]},
    {"name":"Deficit Deadlift","aliases":[],"primary_muscles":["glutes","hamstrings","quads"],"secondary_muscles":["erectors","lats","forearms"],"equipment":"barbell","movement_pattern":"hinge","force_type":"pull","mechanics":"compound","supports_bodyweight":false,"supports_incline":false,"supports_grip":false,"supports_stance":true,"default_rep_range":[3,6],"default_sets":3,"tags":["strength","powerlifting"]},
    {"name":"Snatch-Grip Deadlift","aliases":["Wide-Grip Deadlift"],"primary_muscles":["back","glutes","hamstrings"],"secondary_muscles":["traps","erectors","quads"],"equipment":"barbell","movement_pattern":"hinge","force_type":"pull","mechanics":"compound","supports_bodyweight":false,"supports_incline":false,"supports_grip":false,"supports_stance":true,"default_rep_range":[3,6],"default_sets":3,"tags":["strength","olympic"]},
    {"name":"Barbell Pullover","aliases":["BB Pullover"],"primary_muscles":["lats","chest"],"secondary_muscles":["triceps","serratus"],"equipment":"barbell","movement_pattern":"pull_vertical","force_type":"pull","mechanics":"compound","supports_bodyweight":false,"supports_incline":false,"supports_grip":false,"supports_stance":false,"default_rep_range":[8,12],"default_sets":3,"tags":["hypertrophy"]},
    {"name":"Reverse Barbell Curl","aliases":["Reverse Curl"],"primary_muscles":["forearms","biceps"],"secondary_muscles":[],"equipment":"barbell","movement_pattern":"isolation","force_type":"pull","mechanics":"isolation","supports_bodyweight":false,"supports_incline":false,"supports_grip":false,"supports_stance":false,"default_rep_range":[10,15],"default_sets":3,"tags":["hypertrophy","isolation"]},
    {"name":"Barbell Hip Thrust","aliases":["BB Hip Thrust"],"primary_muscles":["glutes"],"secondary_muscles":["hamstrings","core"],"equipment":"barbell","movement_pattern":"hinge","force_type":"push","mechanics":"compound","supports_bodyweight":false,"supports_incline":false,"supports_grip":false,"supports_stance":false,"default_rep_range":[8,12],"default_sets":3,"tags":["strength","hypertrophy","glute_activation"]},
    {"name":"Seal Row","aliases":["Chest-Supported Barbell Row"],"primary_muscles":["lats","back"],"secondary_muscles":["biceps","rear_deltoid"],"equipment":"barbell","movement_pattern":"pull_horizontal","force_type":"pull","mechanics":"compound","supports_bodyweight":false,"supports_incline":false,"supports_grip":true,"supports_stance":false,"default_rep_range":[8,12],"default_sets":3,"tags":["strength","hypertrophy"]},
    {"name":"Barbell Hack Squat","aliases":["BB Hack Squat"],"primary_muscles":["quads"],"secondary_muscles":["glutes","hamstrings"],"equipment":"barbell","movement_pattern":"squat","force_type":"push","mechanics":"compound","supports_bodyweight":false,"supports_incline":false,"supports_grip":false,"supports_stance":true,"default_rep_range":[6,10],"default_sets":3,"tags":["strength","hypertrophy"]}
  ]
}
